LICENSE
README.md
setup.cfg
setup.py
pycoinpayments/__init__.py
pycoinpayments/apiConfig.py
pycoinpayments/coinpayments.py
pycoinpayments/errors.py
pycoinpayments/sample.py
pycoinpayments/version.py
pycoinpayments.egg-info/PKG-INFO
pycoinpayments.egg-info/SOURCES.txt
pycoinpayments.egg-info/dependency_links.txt
pycoinpayments.egg-info/top_level.txt