Metadata-Version: 2.1
Name: pycoinpayments
Version: 1.0.0
Summary: Coinpayments SDK for python
Home-page: https://github.com/Klynox/python-coinpayments-api-wrapper
Author: Klynox
Author-email: confiyobo@gmail.com
License: UNKNOWN
Download-URL: https://github.com/Klynox/python-coinpayments-api-wrapper/archive/v1.0.0.tar.gz
Keywords: wrapper,sdk,coinpayments,coinpayments-sdk,coinpayments-api-wrapper
Platform: UNKNOWN
Classifier: Development Status :: 5 - Production/Stable
Classifier: Intended Audience :: Developers
Classifier: Programming Language :: Python :: 3
Classifier: License :: OSI Approved :: MIT License
Classifier: Operating System :: OS Independent
License-File: LICENSE
